py42/__init__.py
py42/__version__.py
py42/choices.py
py42/exceptions.py
py42/response.py
py42/usercontext.py
py42/util.py
py42/clients/__init__.py
py42/clients/alertrules.py
py42/clients/alerts.py
py42/clients/archive.py
py42/clients/auditlogs.py
py42/clients/authority.py
py42/clients/cases.py
py42/clients/loginconfig.py
py42/clients/securitydata.py
py42/clients/trustedactivities.py
py42/clients/userriskprofile.py
py42/clients/watchlists.py
py42/clients/_archiveaccess/__init__.py
py42/clients/_archiveaccess/accessorfactory.py
py42/clients/_archiveaccess/restoremanager.py
py42/clients/settings/__init__.py
py42/clients/settings/_converters.py
py42/clients/settings/device_settings.py
py42/clients/settings/org_settings.py
py42/constants/__init__.py
py42/sdk/__init__.py
py42/sdk/queries/__init__.py
py42/sdk/queries/query_filter.py
py42/sdk/queries/alerts/__init__.py
py42/sdk/queries/alerts/alert_query.py
py42/sdk/queries/alerts/util.py
py42/sdk/queries/alerts/filters/__init__.py
py42/sdk/queries/alerts/filters/alert_filter.py
py42/sdk/queries/fileevents/__init__.py
py42/sdk/queries/fileevents/file_event_query.py
py42/sdk/queries/fileevents/util.py
py42/sdk/queries/fileevents/filters/__init__.py
py42/sdk/queries/fileevents/filters/activity_filter.py
py42/sdk/queries/fileevents/filters/cloud_filter.py
py42/sdk/queries/fileevents/filters/device_filter.py
py42/sdk/queries/fileevents/filters/email_filter.py
py42/sdk/queries/fileevents/filters/event_filter.py
py42/sdk/queries/fileevents/filters/exposure_filter.py
py42/sdk/queries/fileevents/filters/file_filter.py
py42/sdk/queries/fileevents/filters/print_filter.py
py42/sdk/queries/fileevents/filters/risk_filter.py
py42/sdk/queries/fileevents/filters/source_filter.py
py42/sdk/queries/fileevents/v1/__init__.py
py42/sdk/queries/fileevents/v2/__init__.py
py42/sdk/queries/fileevents/v2/file_event_query.py
py42/sdk/queries/fileevents/v2/filters/__init__.py
py42/sdk/queries/fileevents/v2/filters/destination.py
py42-1.29.1.dist-info/licenses/LICENSE.md
py42-1.29.1.dist-info/METADATA
py42-1.29.1.dist-info/WHEEL
py42-1.29.1.dist-info/top_level.txt
py42-1.29.1.dist-info/RECORD
