Metadata-Version: 2.4
Name: py42
Version: 1.29.1
Summary: The Official Code42 Python API Client
Home-page: https://github.com/code42/py42
Project-URL: Issue Tracker, https://github.com/code42/py42/issues
Project-URL: Documentation, https://py42docs.code42.com/
Project-URL: Source Code, https://github.com/code42/py42
Classifier: Intended Audience :: Developers
Classifier: Natural Language :: English
Classifier: License :: OSI Approved :: MIT License
Classifier: Programming Language :: Python
Classifier: Programming Language :: Python :: 3
Classifier: Programming Language :: Python :: 3.9
Classifier: Programming Language :: Python :: 3.10
Classifier: Programming Language :: Python :: 3.11
Classifier: Programming Language :: Python :: Implementation :: CPython
Requires-Python: >=3.6, <4
License-File: LICENSE.md
Requires-Dist: urllib3>=1.26.6
Requires-Dist: requests>=2.25.0
Provides-Extra: dev
Requires-Dist: flake8==3.9.2; extra == "dev"
Requires-Dist: pytest==6.2.4; extra == "dev"
Requires-Dist: pytest-cov==2.12.1; extra == "dev"
Requires-Dist: pytest-mock==3.6.1; extra == "dev"
Requires-Dist: tox==3.24.0; extra == "dev"
Provides-Extra: docs
Requires-Dist: sphinx==8.1.3; extra == "docs"
Requires-Dist: myst-parser==4.0.0; extra == "docs"
Requires-Dist: sphinx_rtd_theme==3.0.2; extra == "docs"
Requires-Dist: docutils==0.21.2; extra == "docs"
Dynamic: classifier
Dynamic: description
Dynamic: description-content-type
Dynamic: home-page
Dynamic: license-file
Dynamic: project-url
Dynamic: provides-extra
Dynamic: requires-dist
Dynamic: requires-python
Dynamic: summary
